pypers/__init__.py
pypers/common.py
pypers/execs.py
pypers/cli/__init__.py
pypers/cli/dynamo_manager.py
pypers/cli/ecs_manager.py
pypers/cli/publish.py
pypers/cli/snapshot.py
pypers/cli/stage_gbd.py
pypers/cli/stage_idx.py
pypers/cli/stage_ori.py
pypers/core/__init__.py
pypers/core/constants.py
pypers/core/logger.py
pypers/core/pipelines.py
pypers/core/step.py
pypers/core/supervisor.py
pypers/core/interfaces/__init__.py
pypers/core/interfaces/config/__init__.py
pypers/core/interfaces/config/pypers_schema_db.py
pypers/core/interfaces/config/pypers_storage.py
pypers/core/interfaces/db/__init__.py
pypers/core/interfaces/db/base.py
pypers/core/interfaces/db/cache.py
pypers/core/interfaces/db/dynamodb.py
pypers/core/interfaces/db/dynamodb_orm.py
pypers/core/interfaces/db/secretsdb.py
pypers/core/interfaces/db/test/__init__.py
pypers/core/interfaces/db/test/test_base.py
pypers/core/interfaces/db/test/test_db_config.py
pypers/core/interfaces/db/test/test_db_log.py
pypers/core/interfaces/db/test/test_done_file_db.py
pypers/core/interfaces/db/test/test_dynamo_error.py
pypers/core/interfaces/db/test/test_dynamo_seen.py
pypers/core/interfaces/db/test/test_dynamodb.py
pypers/core/interfaces/db/test/test_secrets.py
pypers/core/interfaces/msgbus/__init__.py
pypers/core/interfaces/msgbus/base.py
pypers/core/interfaces/msgbus/sqs.py
pypers/core/interfaces/msgbus/test/__init__.py
pypers/core/interfaces/msgbus/test/test_base.py
pypers/core/interfaces/msgbus/test/test_sqs.py
pypers/core/interfaces/storage/__init__.py
pypers/core/interfaces/storage/backup.py
pypers/core/interfaces/storage/base.py
pypers/core/interfaces/storage/filesystem.py
pypers/core/interfaces/storage/s3.py
pypers/core/interfaces/storage/test/__init__.py
pypers/core/interfaces/storage/test/test_base.py
pypers/core/interfaces/storage/test/test_s3.py
pypers/core/test/__init__.py
pypers/core/test/folders.txt
pypers/core/test/ftp.py
pypers/core/test/local_fetch.json
pypers/core/test/local_fetch2.json
wipo_gbd_pypers-2.3.118.dist-info/LICENSE.md
wipo_gbd_pypers-2.3.118.dist-info/METADATA
wipo_gbd_pypers-2.3.118.dist-info/WHEEL
wipo_gbd_pypers-2.3.118.dist-info/entry_points.txt
wipo_gbd_pypers-2.3.118.dist-info/top_level.txt
wipo_gbd_pypers-2.3.118.dist-info/RECORD
