Metadata-Version: 2.1
Name: wipo-gbd-pypers
Version: 2.3.118
Summary: Pypers package
Home-page: https://bitbucket.org/wipo_bds/pypers
Author: WIPO GDB team
Author-email: gbd@wipo.int
License: UNKNOWN
Keywords: pypers
Platform: UNKNOWN
Classifier: Programming Language :: Python :: 3.9
License-File: LICENSE.md
Requires-Dist: PyYAML (>=5.3.1)
Requires-Dist: boto3 (>=1.16.1)
Requires-Dist: bs4 (>=0.0.1)
Requires-Dist: coverage
Requires-Dist: dicttoxml (>=1.7.4)
Requires-Dist: dynamorm (>=0.11.0)
Requires-Dist: ftputil (>=4.0.0)
Requires-Dist: jinja2 (==2.11.2)
Requires-Dist: lxml (>=4.6.1)
Requires-Dist: markupsafe (==2.0.1)
Requires-Dist: marshmallow
Requires-Dist: mock
Requires-Dist: networkx (>=2.5)
Requires-Dist: nose
Requires-Dist: numpy (>=1.19.2)
Requires-Dist: opencv-python (>=4.4.0.44)
Requires-Dist: pandas (<=2.2.3,>=1.1.3)
Requires-Dist: paramiko (==3.5.1)
Requires-Dist: patool (>=1.12)
Requires-Dist: psutil (>=5.7.2)
Requires-Dist: pymongo (>=3.11.0)
Requires-Dist: pyunpack (>=0.2.2)
Requires-Dist: rarfile (==4.2)
Requires-Dist: requests (>=2.25.1)
Requires-Dist: scipy (>=1.5.3)
Requires-Dist: tabulate (>=0.8.7)
Requires-Dist: xmltodict (>=0.12.0)
